<?xml version="1.0" encoding="UTF-8" ?>
<!--Template for find product in the pos-->
<templates id="template" xml:space="preserve">
    <t t-name="product_detail_search.FindProductScreen" owl="1">
       <div class="clientlist-screen screen">
           <div class="screen-content">
               <div class="top-content">
                   <div class="order-button floor-button d-flex align-items-center gap-2 px-4 fw-bolder cursor-pointer"
                        t-on-click="() => this.back()">
                       <i class="fa fa-2x fa-angle-left pb-1" role="img"
                          aria-label="Go Back" title="Go Back"/>
                       <span>Back</span>
                   </div>
               </div>
               <form class="form_scan_product">
                   <h2>Scan Your Product</h2>
                   <h4>Please Scan a Product To get the details</h4>
                </form>
           </div>
       </div>
   </t>
</templates>
