<?xml version="1.0" encoding="utf-8"?>
<odoo>
    <!--Modern Template Preview-->
    <template id="report_preview_modern">
        <t t-call="web.html_preview_container">
            <t t-call="web.external_layout">
                <div class="page">
                    <div t-attf-style=" background-color:#{company.document_layout_id.base_color};padding:2% ;color:#{company.document_layout_id.heading_text_color};">
                        <h2>
                            <div t-attf-style="color:##FFFFFF">
                                Order# SO0003
                            </div>
                        </h2>
                        <div id="informations"
                             class="row mt32 mb32">
                            <div class="col-auto mw-100 mb-2"
                                 name="order_date"
                                 t-attf-style="color:##FFFFFF;">
                                <p>Order Date:
                                </p>
                                <p class="m-0">07/08/2020
                                </p>
                            </div>
                            <div class="col-auto mw-100 mb-2"
                                 name="sales"
                                 t-attf-style="color:##FFFFFF;">
                                <p>Sales Person
                                </p>
                                <p class="m-0">Mitchell
                                    Admin
                                </p>
                            </div>
                        </div>
                    </div>
                </div>
                <div class="pt-5">
                    <div class="address row">
                        <div name="address" class="col-md-5 ml-auto">
                            <div itemprop="address">
                                <div class="d-flex align-items-baseline">
                                    <span class="w-100 o_force_ltr"
                                          itemprop="streetAddress">
                                        Deco Addict
                                        <br/>
                                        77 Santa Barbara
                                        Rd<br/>Pleasant Hill CA
                                        94523<br/>United States
                                        <br/>
                                    </span>
                                </div>
                            </div>
                        </div>
                    </div>
                </div>
                <div class="page">
                    <br/>
                    <br/>
                    <table class="table table-sm table-borderless"
                           style="padding-top:20px;width:100%">
                        <tr>
                            <th class='text-center'
                                t-attf-style=" background-color:#{company.document_layout_id.base_color};color:#{company.document_layout_id.heading_text_color};">
                                Description
                            </th>
                            <th class='text-center'
                                t-attf-style=" background-color:#{company.document_layout_id.base_color};color:#{company.document_layout_id.heading_text_color};">
                                Quantity
                            </th>
                            <th class='text-center'
                                t-attf-style=" background-color:#{company.document_layout_id.base_color};color:#{company.document_layout_id.heading_text_color};">
                                Unit Price
                            </th>
                            <th class='text-center'
                                t-attf-style=" background-color:#{company.document_layout_id.base_color};color:#{company.document_layout_id.heading_text_color};">
                                Taxes
                            </th>
                            <th class='text-center'
                                t-attf-style=" background-color:#{company.document_layout_id.base_color};color:#{company.document_layout_id.heading_text_color};">
                                Price
                            </th>
                        </tr>
                        <!--Order lines body-->
                        <tr>
                            <td t-attf-style="color:#{company.document_layout_id.text_color};">
                                <font>
                                    <p class="text-center">[FURN_8999]
                                        Three-Seat Sofa
                                    </p>
                                </font>
                            </td>
                            <td t-attf-style="color:#{company.document_layout_id.text_color};">
                                <font>
                                    <p class="text-center">5.000</p>
                                </font>
                            </td>
                            <td t-attf-style="color:#{company.document_layout_id.text_color};">
                                <font>
                                    <p class="text-center">1,500.00</p>
                                </font>
                            </td>
                            <td t-attf-style="color:#{company.document_layout_id.text_color};">
                                <font>
                                    <p class="text-center">15.00%</p>
                                </font>
                            </td>
                            <td t-attf-style="color:#{company.document_layout_id.text_color};">
                                <font>
                                    <p class="text-center">7,500.00</p>
                                </font>
                            </td>
                        </tr>
                        <tr>
                            <td t-attf-style="color:#{company.document_layout_id.text_color};">
                                <font>
                                    <p class="text-center">FURN_8220] Four
                                        Person Desk
                                        <br/>
                                        Four person modern office
                                        workstation
                                    </p>
                                </font>
                            </td>
                            <td t-attf-style="color:#{company.document_layout_id.text_color};">
                                <font>
                                    <p class="text-center">5.000</p>
                                </font>
                            </td>
                            <td t-attf-style="color:#{company.document_layout_id.text_color};">
                                <font>
                                    <p class="text-center">23,500.00</p>
                                </font>
                            </td>
                            <td t-attf-style="color:#{company.document_layout_id.text_color};">
                                <font>
                                    <p class="text-center">15.00%</p>
                                </font>
                            </td>
                            <td t-attf-style="color:#{company.document_layout_id.text_color};">
                                <font>
                                    <p class="text-center">117,500.00</p>
                                </font>
                            </td>
                        </tr>
                    </table>
                    <div>
                        <div class="clearfix mb-4">
                            <div id="total" class="row">
                                <div t-attf-class="#{'col-6' if report_type != 'html' else 'col-sm-7 col-md-6'} ms-auto">
                                    <table class="table table-sm table-borderless"
                                           style="page-break-inside: avoid;">
                                        <tbody>
                                            <tr class="border-black o_subtotal">
                                                <td t-attf-style="color:#{company.document_layout_id.text_color};">
                                                    <strong t-attf-style="color:#{company.document_layout_id.text_color};">
                                                        Untaxed Amount
                                                    </strong>
                                                </td>
                                                <td class="text-end"
                                                    t-attf-style="color:#{company.document_layout_id.text_color};">
                                                    <span>$
                                                        <span class="oe_currency_value">
                                                            125,000.00
                                                        </span>
                                                    </span>
                                                </td>
                                            </tr>
                                            <tr style="">
                                                <td>
                                                    <span class="text-nowrap">
                                                        Tax 15%
                                                    </span>
                                                </td>
                                                <td class="text-end o_price_total">
                                                    <span class="text-nowrap">
                                                        $
                                                        18,750.00
                                                    </span>
                                                </td>
                                            </tr>
                                            <tr class="border-black o_total">
                                                <td>
                                                    <strong t-attf-style="color:#{company.document_layout_id.customer_text_color};">
                                                        Total
                                                    </strong>
                                                </td>
                                                <td class="text-end">
                                                    <span class="text-nowrap"
                                                          t-attf-style="color:#{company.document_layout_id.customer_text_color};">
                                                        $
                                                        <span class="oe_currency_value">
                                                            143,750.00
                                                        </span>
                                                    </span>
                                                </td>
                                            </tr>
                                        </tbody>
                                    </table>
                                </div>
                            </div>
                        </div>
                    </div>
                </div>
            </t>
        </t>
    </template>
</odoo>
