<?xml version="1.0" encoding="UTF-8" ?>
<!-- The view inherits from the standard "account.res_config_settings_view_form" view and adds the two new fields in a separate section.-->
<odoo>
    <record id="res_config_settings_view_form" model="ir.ui.view">
        <field name="name">res.config.settings.view.form.inherit.automatic.invoice.and.post</field>
        <field name="model">res.config.settings</field>
        <field name="inherit_id" ref="account.res_config_settings_view_form"/>
        <field name="arch" type="xml">
            <xpath expr="//div[@id='analytic']" position="after">
                <div class="row mt16 o_settings_container">
                    <div class="content-group mt16">
                        <h2>Auto Invoice Post</h2>
                        <div class="col-12 col-lg-6 o_setting_box">
                            <div class="o_setting_left_pane">
                                <field name="is_create_invoice_delivery_validate"/>
                            </div>
                            <div class="o_setting_right_pane">
                                <label for="is_create_invoice_delivery_validate"/>
                                <div class="text-muted">
                                    Create and post invoice on delivery validate
                                </div>
                            </div>
                        </div>
                        <div class="col-12 col-lg-6 o_setting_box">
                                     <div class="o_setting_left_pane">
                                <field name="is_auto_send_invoice"/>
                            </div>
                            <div class="o_setting_right_pane">
                                <label for="is_auto_send_invoice"/>
                                <div class="text-muted">
                                    Enable to send invoice to customer on delivery validate
                                </div>
                            </div>
                        </div>
                    </div>
                </div>
            </xpath>
        </field>
    </record>
</odoo>