<?xml version="1.0" encoding="utf-8"?>
<odoo>
    <!--    Inherit product brand for adding field is_featured_brand-->
    <record id="product_brand_view_form" model="ir.ui.view">
        <field name="name">product.brand.view.form.inherit.featured.brand.snippet</field>
        <field name="model">product.brand</field>
        <field name="inherit_id" ref="product_brand_sale.product_brand_view"/>
        <field name="arch" type="xml">
            <field name="product_count" position="after">
                <field name="is_featured_brand"/>
            </field>
        </field>
    </record>
</odoo>