<?xml version="1.0" encoding="utf-8"?>
<odoo>
<!--    Form page for the website pre-book model -->
    <record id="website_prebook_view_form" model="ir.ui.view">
        <field name="name">website.prebook.view.form</field>
        <field name="model">website.prebook</field>
        <field name="arch" type="xml">
            <form>
                <header>
                    <button name="action_confirm" data-hotkey="v" string="Confirm" type="object"
                            groups="base.group_user" invisible="state != 'draft'"/>
                    <field name="state" widget="statusbar"/>
                </header>
                <sheet>
                    <div class="oe_button_box" name="button_box">
                        <button name="action_view_sale_order" type="object" class="oe_stat_button"
                                icon="fa-pencil-square-o"
                                invisible="state != 'confirm'">
                            <div class="o_stat_info">
                                <span class="o_stat_text">Sale Order</span>
                            </div>
                        </button>
                    </div>
                    <div class="oe_title">
                        <h1>
                            <field name="reference" readonly="1"/>
                        </h1>
                    </div>
                    <group>
                        <group>
                            <field name="partner_id"/>
                        </group>
                        <group>
                            <field name="booking_date"/>
                        </group>
                        <group>
                            <field name="product_id"/>
                            <field name="quantity"/>
                        </group>
                        <group>
                            <field name="website_id"/>
                        </group>
                    </group>
                </sheet>
            </form>
        </field>
    </record>
<!--    Tree page for the website pre-book model -->
    <record id="website_prebook_view_tree" model="ir.ui.view">
        <field name="name">website.prebook.view.tree</field>
        <field name="model">website.prebook</field>
        <field name="arch" type="xml">
            <tree default_order="reference desc">
                <field name="reference"/>
                <field name="partner_id"/>
                <field name="product_id"/>
                <field name="quantity"/>
                <field name="booking_date"/>
            </tree>
        </field>
    </record>
<!--Menu action for the pre-book menu-->
    <record id="action_prebook_menu" model="ir.actions.act_window">
        <field name="name">Pre Bookings</field>
        <field name="type">ir.actions.act_window</field>
        <field name="res_model">website.prebook</field>
        <field name="view_mode">tree,kanban,form</field>
        <field name="help" type="html">
            <p class="o_view_nocontent_smiling_face">
                Create!
            </p>
        </field>
    </record>
<!--    Menu action for the pre-book main menu-->
    <record id="action_pre_book_main_menu" model="ir.actions.act_window">
        <field name="name">Pre Bookings</field>
        <field name="type">ir.actions.act_window</field>
        <field name="res_model">website.prebook</field>
        <field name="view_mode">tree,kanban,form</field>
        <field name="help" type="html">
            <p class="o_view_nocontent_smiling_face">
                Create!
            </p>
        </field>
    </record>
<!--    Menu for the pre-booking-->
    <menuitem id="website_prebook_root"
              name="Pre Bookings"
              parent="website_sale.menu_ecommerce"
              action="action_prebook_menu"
              sequence="10"/>
</odoo>